mo_dots/__init__.py
mo_dots/datas.py
mo_dots/fields.py
mo_dots/lists.py
mo_dots/logging.py
mo_dots/nones.py
mo_dots/objects.py
mo_dots/utils.py
mo_dots-10.685.25166.dist-info/licenses/LICENSE
mo_dots-10.685.25166.dist-info/METADATA
mo_dots-10.685.25166.dist-info/WHEEL
mo_dots-10.685.25166.dist-info/top_level.txt
mo_dots-10.685.25166.dist-info/RECORD
