Metadata-Version: 2.4
Name: mo-dots
Version: 10.685.25166
Summary: More Dots! Dot-access to Python dicts like Javascript
Home-page: https://github.com/klahnakoski/mo-dots
Author: Kyle Lahnakoski
Author-email: kyle@lahnakoski.com
License: MPL 2.0
Classifier: Development Status :: 5 - Production/Stable
Classifier: Topic :: Software Development :: Libraries
Classifier: Topic :: Software Development :: Libraries :: Python Modules
Classifier: License :: OSI Approved :: Mozilla Public License 2.0 (MPL 2.0)
Classifier: Programming Language :: Python :: 3.8
Classifier: Programming Language :: Python :: 3.9
Classifier: Programming Language :: Python :: 3.10
Classifier: Programming Language :: Python :: 3.11
Classifier: Programming Language :: Python :: 3.12
Classifier: Programming Language :: Python :: 3.13
License-File: LICENSE
Requires-Dist: mo-future==7.685.25166
Requires-Dist: mo-imports==7.685.25166
Provides-Extra: tests
Requires-Dist: mo-logs>=8.672.25036; extra == "tests"
Requires-Dist: mo-json>=6.672.25036; extra == "tests"
Requires-Dist: mo-threads>=6.672.25036; extra == "tests"
Requires-Dist: mo-testing>=8.674.25037; extra == "tests"
Requires-Dist: pyLibrary>=3.264.22338; extra == "tests"
Requires-Dist: mo-math>=7.672.25036; extra == "tests"
Requires-Dist: mo-times>=5.672.25036; extra == "tests"
Requires-Dist: jx-elasticsearch>=3.99.20292; extra == "tests"
Requires-Dist: beautifulsoup4>=4.13.3; extra == "tests"
Dynamic: author
Dynamic: author-email
Dynamic: classifier
Dynamic: description
Dynamic: description-content-type
Dynamic: home-page
Dynamic: license
Dynamic: license-file
Dynamic: provides-extra
Dynamic: requires-dist
Dynamic: summary
